ai_safety_guardrails/__init__.py
ai_safety_guardrails/decorators.py
ai_safety_guardrails/cli/__init__.py
ai_safety_guardrails/cli/config.py
ai_safety_guardrails/cli/create.py
ai_safety_guardrails/cli/main.py
ai_safety_guardrails/cli/models.py
ai_safety_guardrails/cli/__pycache__/__init__.cpython-313.pyc
ai_safety_guardrails/cli/__pycache__/config.cpython-313.pyc
ai_safety_guardrails/cli/__pycache__/create.cpython-313.pyc
ai_safety_guardrails/cli/__pycache__/main.cpython-313.pyc
ai_safety_guardrails/cli/__pycache__/models.cpython-313.pyc
ai_safety_guardrails/core/__init__.py
ai_safety_guardrails/core/detector_config.py
ai_safety_guardrails/core/model_manager.py
ai_safety_guardrails/core/safety_guard.py
ai_safety_guardrails/detectors/__init__.py
ai_safety_guardrails/detectors/base_detector.py
ai_safety_guardrails/detectors/fact_check.py
ai_safety_guardrails/detectors/pii.py
ai_safety_guardrails/detectors/prompt_injection.py
ai_safety_guardrails/detectors/spam.py
ai_safety_guardrails/detectors/topics.py
ai_safety_guardrails/detectors/toxicity.py
ai_safety_guardrails/integrations/__init__.py
ai_safety_guardrails/integrations/ollama_client.py
ai_safety_guardrails/integrations/openai_client.py
ai_safety_guardrails/templates/__init__.py
ai_safety_guardrails/templates/creator.py
ai_safety_guardrails/templates/__pycache__/__init__.cpython-313.pyc
ai_safety_guardrails/templates/__pycache__/creator.cpython-313.pyc
ai_safety_guardrails/templates/chat/.env.example.j2
ai_safety_guardrails/templates/chat/README.md.j2
ai_safety_guardrails/templates/chat/config.yml.j2
ai_safety_guardrails/templates/chat/main.py.j2
ai_safety_guardrails/templates/chat/requirements.txt.j2
ai_safety_guardrails/utils/__init__.py
ai_safety_guardrails/utils/exceptions.py
ai_safety_guardrails/utils/logger.py
ai_safety_guardrails/utils/__pycache__/__init__.cpython-313.pyc
ai_safety_guardrails/utils/__pycache__/exceptions.cpython-313.pyc
ai_safety_guardrails/utils/__pycache__/logger.cpython-313.pyc
ai_safety_guardrails-1.0.0.dist-info/licenses/LICENSE
ai_safety_guardrails-1.0.0.dist-info/METADATA
ai_safety_guardrails-1.0.0.dist-info/WHEEL
ai_safety_guardrails-1.0.0.dist-info/entry_points.txt
ai_safety_guardrails-1.0.0.dist-info/top_level.txt
ai_safety_guardrails-1.0.0.dist-info/RECORD
