Metadata-Version: 2.4
Name: ai-safety-guardrails
Version: 1.0.0
Summary: Comprehensive AI safety package for LLM applications
Home-page: https://github.com/udsy19/NemoGaurdrails-Package
Author: Udaya Vijay Anand
Author-email: Udaya Vijay Anand <udayatejas2004@gmail.com>
License: MIT
Project-URL: Homepage, https://github.com/udsy19/NemoGaurdrails-Package
Project-URL: Documentation, https://github.com/udsy19/NemoGaurdrails-Package/blob/main/README.md
Project-URL: Repository, https://github.com/udsy19/NemoGaurdrails-Package
Project-URL: Issues, https://github.com/udsy19/NemoGaurdrails-Package/issues
Keywords: ai,safety,guardrails,llm,machine-learning,security,content-filtering,toxicity,pii,openai,ollama,transformers,nemo-guardrails
Classifier: Development Status :: 4 - Beta
Classifier: Intended Audience :: Developers
Classifier: License :: OSI Approved :: MIT License
Classifier: Programming Language :: Python :: 3
Classifier: Programming Language :: Python :: 3.9
Classifier: Programming Language :: Python :: 3.10
Classifier: Programming Language :: Python :: 3.11
Classifier: Programming Language :: Python :: 3.12
Classifier: Programming Language :: Python :: 3.13
Classifier: Topic :: Software Development :: Libraries :: Python Modules
Classifier: Topic :: Security
Classifier: Topic :: Scientific/Engineering :: Artificial Intelligence
Classifier: Topic :: Internet :: WWW/HTTP :: Dynamic Content :: Content Management System
Requires-Python: >=3.9
License-File: LICENSE
Requires-Dist: pyyaml>=6.0.1
Requires-Dist: requests>=2.31.0
Requires-Dist: python-dotenv>=1.0.0
Requires-Dist: pydantic>=2.5.0
Requires-Dist: torch>=2.1.0
Requires-Dist: transformers>=4.35.0
Requires-Dist: sentence-transformers>=2.2.0
Requires-Dist: tokenizers>=0.15.0
Requires-Dist: huggingface-hub>=0.19.0
Requires-Dist: safetensors>=0.4.0
Requires-Dist: numpy>=1.26.0
Requires-Dist: pandas>=2.1.0
Requires-Dist: scikit-learn>=1.3.0
Requires-Dist: spacy>=3.7.0
Requires-Dist: loguru>=0.7.0
Requires-Dist: jinja2>=3.1.0
Requires-Dist: click>=8.0.0
Requires-Dist: rich>=13.0.0
Requires-Dist: typer>=0.9.0
Provides-Extra: templates
Requires-Dist: fastapi>=0.104.1; extra == "templates"
Requires-Dist: uvicorn[standard]>=0.24.0; extra == "templates"
Requires-Dist: streamlit>=1.25.0; extra == "templates"
Requires-Dist: websockets>=12.0; extra == "templates"
Requires-Dist: python-multipart>=0.0.6; extra == "templates"
Provides-Extra: gpu
Requires-Dist: torch[cuda]>=2.1.0; extra == "gpu"
Provides-Extra: dev
Requires-Dist: pytest>=7.4.0; extra == "dev"
Requires-Dist: pytest-asyncio>=0.21.0; extra == "dev"
Requires-Dist: black>=23.0.0; extra == "dev"
Requires-Dist: flake8>=6.0.0; extra == "dev"
Requires-Dist: mypy>=1.5.0; extra == "dev"
Requires-Dist: isort>=5.12.0; extra == "dev"
Provides-Extra: docs
Requires-Dist: sphinx>=7.0.0; extra == "docs"
Requires-Dist: sphinx-rtd-theme>=1.3.0; extra == "docs"
Requires-Dist: myst-parser>=2.0.0; extra == "docs"
Provides-Extra: monitoring
Requires-Dist: prometheus-client>=0.19.0; extra == "monitoring"
Requires-Dist: psutil>=5.9.0; extra == "monitoring"
Provides-Extra: full
Requires-Dist: fastapi>=0.104.1; extra == "full"
Requires-Dist: uvicorn[standard]>=0.24.0; extra == "full"
Requires-Dist: streamlit>=1.25.0; extra == "full"
Requires-Dist: websockets>=12.0; extra == "full"
Requires-Dist: python-multipart>=0.0.6; extra == "full"
Requires-Dist: prometheus-client>=0.19.0; extra == "full"
Requires-Dist: psutil>=5.9.0; extra == "full"
Requires-Dist: gradio>=4.0.0; extra == "full"
Requires-Dist: jupyter>=1.0.0; extra == "full"
Dynamic: author
Dynamic: home-page
Dynamic: license-file
Dynamic: requires-python
